
{
  "data": [
    {
      "id": 1,
      "image":"https://encrypted-tbn0.gstatic.com/images?q=tbn:ANd9GcSW-tC1SVoshvTVawIAFCFJCyQOdOwE2tvgcQ&usqp=CAU",
      "name": "John Doe",
      "operating_company": "ABC Inc.",
      "company_type": "Corporation",
      "law_firm_or_business_name": "Law Firm XYZ",
      "address1": "123 Main St",
      "city": "New York",
      "state": "NY",
      "country": "USA",
      "zipcode": "10001",
      "phone_number": "555-123-4567",
      "firm_speciality": "Corporate Law",
      "case_management": "Lawyer A",
      "account_manager": "Jane Smith",
      "new_user_invited": "john.doe@example.com",
      "new_user_added": "jane.smith@example.com",
      "payment_method_change": "john.doe@example.com"
    }
  ]
}
